{"markers":[{"name":"Hit","position":1.791044776119403},{"name":"Small Fish","position":1.791044776119403},{"name":"Top","position":1.791044776119403},{"name":"Hit","position":2.4554051137696455},{"name":"Advance","position":3.582089552238806},{"name":"Hit","position":5.373134328358209},{"name":"Medium Fish","position":5.373134328358209},{"name":"Left","position":5.373134328358209},{"name":"Hit","position":6.044776119402985},{"name":"Hit","position":6.7164179104477615},{"name":"Advance","position":7.164179104477612},{"name":"Hit","position":8.955223880597016},{"name":"Small Fish","position":8.955223880597016},{"name":"Bottom","position":8.955223880597016},{"name":"Hit","position":9.626865671641792},{"name":"Advance","position":10.746268656716419},{"name":"Hit","position":12.537313432835822},{"name":"Medium Fish","position":12.537313432835822},{"name":"Right","position":12.537313432835822},{"name":"Hit","position":13.208955223880599},{"name":"Hit","position":13.880597014925376},{"name":"Advance","position":14.328358208955224}]}